{"mean":{"confidence_interval":{"confidence_level":0.95,"lower_bound":3331342.2077833335,"upper_bound":3338489.846116667},"point_estimate":3335054.451999999,"standard_error":1823.8441859899444},"median":{"confidence_interval":{"confidence_level":0.95,"lower_bound":3335509.8333333335,"upper_bound":3340680.8},"point_estimate":3337857.7333333334,"standard_error":1085.6797364552308},"median_abs_dev":{"confidence_interval":{"confidence_level":0.95,"lower_bound":8717.687845230103,"upper_bound":16140.769393443785},"point_estimate":12154.45342421495,"standard_error":1856.2849792891045},"slope":null,"std_dev":{"confidence_interval":{"confidence_level":0.95,"lower_bound":13609.636923110662,"upper_bound":22715.090477224716},"point_estimate":18311.14231579321,"standard_error":2334.4848270837647}}