{"mean":{"confidence_interval":{"confidence_level":0.95,"lower_bound":99779.12746398355,"upper_bound":100171.94347289742},"point_estimate":99929.62508165302,"standard_error":106.0747917967833},"median":{"confidence_interval":{"confidence_level":0.95,"lower_bound":99799.4310967742,"upper_bound":99879.51206896552},"point_estimate":99841.20262704566,"standard_error":23.85299676854938},"median_abs_dev":{"confidence_interval":{"confidence_level":0.95,"lower_bound":143.0677878401068,"upper_bound":263.7963575597792},"point_estimate":198.69770567702332,"standard_error":31.82591227237327},"slope":{"confidence_interval":{"confidence_level":0.95,"lower_bound":99877.83978503685,"upper_bound":100032.56546113075},"point_estimate":99939.81971567903,"standard_error":40.81890829438073},"std_dev":{"confidence_interval":{"confidence_level":0.95,"lower_bound":224.32960870589267,"upper_bound":1786.073776435278},"point_estimate":1070.7970621993193,"standard_error":507.53871358172864}}